fspdf/__init__.py
fspdf/__main__.py
fspdf/fspdf.py
fspdf-0.1.5.dist-info/LICENSE
fspdf-0.1.5.dist-info/METADATA
fspdf-0.1.5.dist-info/WHEEL
fspdf-0.1.5.dist-info/entry_points.txt
fspdf-0.1.5.dist-info/top_level.txt
fspdf-0.1.5.dist-info/RECORD
