Metadata-Version: 2.1
Name: fspdf
Version: 0.1.5
Summary: Fill and sign any PDF.
Home-page: https://github.com/kaiec/fspdf/
Author: Kai Eckert
Author-email: hallo@kaiec.de
License: MIT
Keywords: PDF forms fill sign annotate
License-File: LICENSE
Requires-Dist: Pillow
